{
    "type": [
        "h-product"
    ],
    "properties": {
        "brand": [
            "p-brand"
        ],
        "category": [
            "p-category"
        ],
        "description": [
            "p-description"
        ],
        "fn": [
            "p-name"
        ],
        "identifier": [
            "u-identifier"
        ],
        "photo": [
            "u-photo"
        ],
        "price": [
            "p-price"
        ],
        "review": [
            "hreview",
            "p-review"
        ],
        "url": [
            "u-url"
        ]
    }
}
